powerpoint_generative_ai/__init__.py
powerpoint_generative_ai/ppt_analyzer.py
powerpoint_generative_ai/ppt_generator.py
powerpoint_generative_ai/domain/__init__.py
powerpoint_generative_ai/domain/constants.py
powerpoint_generative_ai/domain/exceptions.py
powerpoint_generative_ai/domain/prompts.py
powerpoint_generative_ai/ppt/__init__.py
powerpoint_generative_ai/ppt/ppt_creator.py
powerpoint_generative_ai/ppt/ppt_loader.py
powerpoint_generative_ai/utils/__init__.py
powerpoint_generative_ai/utils/image_caption_gen.py
powerpoint_generative_ai/utils/pinecone_utils.py
powerpoint_generative_ai/utils/utils.py
powerpoint_generative_ai-0.1.8.dist-info/LICENSE
powerpoint_generative_ai-0.1.8.dist-info/METADATA
powerpoint_generative_ai-0.1.8.dist-info/WHEEL
powerpoint_generative_ai-0.1.8.dist-info/top_level.txt
powerpoint_generative_ai-0.1.8.dist-info/RECORD
